{
    "domain_id": "HEALTHCARE_TRIAGE_V1",
    "domain_name": "Emergency Department Triage Monitor",
    "version": "1.0.0",
    "entities": [
        "heart_rate",
        "respiratory_rate",
        "blood_pressure_systolic",
        "blood_pressure_diastolic",
        "oxygen_saturation",
        "glucose_mg_dl"
    ],
    "constraints": [
        {
            "id": "HR_01",
            "entity": "heart_rate",
            "operator": "RANGE",
            "value": [
                40,
                150
            ],
            "description": "Cardiac Rate Safety (40-150 bpm)",
            "severity": "IMPOSSIBLE",
            "evidence_source": "Standard Advanced Life Support Protocol"
        },
        {
            "id": "SPO2_01",
            "entity": "oxygen_saturation",
            "operator": "GT",
            "value": 88.0,
            "description": "Oxygen Saturation Threshold (> 88%)",
            "severity": "TOXIC",
            "evidence_source": "Respiratory Crisis Reference"
        },
        {
            "id": "GLU_01",
            "entity": "glucose_mg_dl",
            "operator": "GT",
            "value": 50.0,
            "description": "Hypoglycemic Critical Threshold (> 50 mg/dL)",
            "severity": "TOXIC",
            "evidence_source": "Endocrine Emergency Handbook"
        }
    ]
}